Metadata-Version: 2.1
Name: howbigami
Version: 0.1.3
Summary: Treemap visualization of component sizes
Home-page: https://github.com/llansky3/howbigami
Author: Lukas Lansky
Author-email: lukas.lansky@suse.com
License: Apache License 2.0
Platform: UNKNOWN
